np_session/__init__.py
np_session/components/__init__.py
np_session/components/info.py
np_session/components/lims_manifests.py
np_session/components/mixins.py
np_session/components/paths.py
np_session/components/platform_json.py
np_session/components/settings_xml.py
np_session/components/state.py
np_session/databases/__init__.py
np_session/databases/data_getters.py
np_session/databases/firebase_state.py
np_session/databases/lims2.py
np_session/databases/mtrain.py
np_session/databases/redis_state.py
np_session/exceptions.py
np_session/jobs/__init__.py
np_session/jobs/lims_upload.py
np_session/jobs/sync_states.py
np_session/session.py
np_session/subclasses/__init__.py
np_session/subclasses/dynamic_routing_pilot.py
np_session/subclasses/pipeline.py
np_session/subclasses/templeton_pilot.py
np_session/tasks.py
np_session/utils.py
np_session-0.6.48.dist-info/WHEEL
np_session-0.6.48.dist-info/METADATA
np_session-0.6.48.dist-info/RECORD
