Metadata-Version: 2.1
Name: np-session
Version: 0.6.48
Summary: Tools for accessing data, metadata, and jobs related to ecephys and behavior sessions for the Mindscope Neuropixels team.
Author-email: Ben Hardcastle <ben.hardcastle@alleninstitute.org>,Arjun Sridhar <arjun.sridhar@alleninstitute.org>,Chris Mochizuki <chrism@alleninstitute.org>
Requires-Python: >=3.7
Classifier: License :: OSI Approved :: MIT License
Classifier: Operating System :: OS Independent
Classifier: Programming Language :: Python :: 3
Requires-Dist: backports.cached-property
Requires-Dist: firebase-admin>=6.1.0
Requires-Dist: np-tools>=0.1.6
Requires-Dist: np_config>=0.4.32
Requires-Dist: np_logging>=0.3.8
Requires-Dist: psycopg2-binary>=2
Requires-Dist: pydantic>=2.0.0
Requires-Dist: redis<=4.1.4
Requires-Dist: requests>=2
Requires-Dist: typing-extensions>=4
Provides-Extra: dev
Requires-Dist: mypy>=0.910; extra == "dev"
Requires-Dist: types-requests>=2; extra == "dev"
Requires-Dist: pytest; extra == "dev"
Requires-Dist: pytest-cov; extra == "dev"
Requires-Dist: blue>=0.9.1; extra == "dev"
Requires-Dist: coverage[toml]>=7.2.2; extra == "dev"
Requires-Dist: pdm>=2.4.9; extra == "dev"
Requires-Dist: bump>=1.3.2; extra == "dev"
Requires-Dist: types-backports>=0.1.3; extra == "dev"
Requires-Dist: ruff>=0.0.260; extra == "dev"
Project-URL: Bug Tracker, https://github.com/alleninstitute/np_session/issues
Project-URL: Repository, https://github.com/alleninstitute/np_session
